lala_esp_bool_parser/__init__.py
lala_esp_bool_parser/bool_parser.py
lala_esp_bool_parser/constants.py
lala_esp_bool_parser/soc_header.py
lala_esp_bool_parser/utils.py
lala_esp_bool_parser-0.1.1.dist-info/LICENSE
lala_esp_bool_parser-0.1.1.dist-info/WHEEL
lala_esp_bool_parser-0.1.1.dist-info/METADATA
lala_esp_bool_parser-0.1.1.dist-info/RECORD
